{
  "meta": {
    "key": "beug06-vesiculatae.json",
    "title": "6. Vesiculatae (Beug)",
    "locale": "nl",
    "source": "Beug",
    "note": "-",
    "stepCount": 5,
    "start": "1"
  },
  "start": "1",
  "steps": {
    "1": {
      "id": "1",
      "type": "step",
      "note": "-",
      "choices": [
        {
          "label": "PK oblaat, met een ringvormige, equatoriaal verlopende luchtzak, die ook in vele kleine blaasjes (Vesiculae) opgelost kan zijn (tabel 3: 4–5, fig. 5p).",
          "next": null,
          "id": {
            "name": "6.1 Tsuga (Blz... 51)",
            "size": "-",
            "source": "-",
            "note": "-",
            "text": "-",
            "incomplete": false,
            "images": [
              {
                "image": "../../assets/images/non-pollen/placeholder.png",
                "imageWidthPx": 1
              },
              {
                "image": "../../assets/images/non-pollen/placeholder.png",
                "imageWidthPx": 1
              },
              {
                "image": "../../assets/images/non-pollen/placeholder.png",
                "imageWidthPx": 1
              },
              {
                "image": "../../assets/images/non-pollen/placeholder.png",
                "imageWidthPx": 1
              }
            ]
          },
          "outcome": null,
          "images": [
            {
              "image": "../../assets/images/non-pollen/placeholder.png",
              "imageWidthPx": 1
            },
            {
              "image": "../../assets/images/non-pollen/placeholder.png",
              "imageWidthPx": 1
            },
            {
              "image": "../../assets/images/non-pollen/placeholder.png",
              "imageWidthPx": 1
            },
            {
              "image": "../../assets/images/non-pollen/placeholder.png",
              "imageWidthPx": 1
            }
          ]
        },
        {
          "label": "PK met twee luchtzakken.",
          "next": "2",
          "id": null,
          "outcome": null,
          "images": [
            {
              "image": "../../assets/images/non-pollen/placeholder.png",
              "imageWidthPx": 1
            },
            {
              "image": "../../assets/images/non-pollen/placeholder.png",
              "imageWidthPx": 1
            },
            {
              "image": "../../assets/images/non-pollen/placeholder.png",
              "imageWidthPx": 1
            },
            {
              "image": "../../assets/images/non-pollen/placeholder.png",
              "imageWidthPx": 1
            }
          ]
        }
      ]
    },
    "2": {
      "id": "2",
      "type": "step",
      "note": "-",
      "choices": [
        {
          "label": "Exine van het PollenMiddenDeel (PMT) dorsaal (proximaal) tot 4 µm dik (zelden tot 4,5 µm; let op *Cedrus* met 4–7 µm).",
          "next": "3",
          "id": null,
          "outcome": null,
          "images": [
            {
              "image": "../../assets/images/non-pollen/placeholder.png",
              "imageWidthPx": 1
            },
            {
              "image": "../../assets/images/non-pollen/placeholder.png",
              "imageWidthPx": 1
            },
            {
              "image": "../../assets/images/non-pollen/placeholder.png",
              "imageWidthPx": 1
            },
            {
              "image": "../../assets/images/non-pollen/placeholder.png",
              "imageWidthPx": 1
            }
          ]
        },
        {
          "label": "Exine van het PMT dorsaal dikker dan 5 µm (soms *Cedrus* met 4–7 µm).",
          "next": "5",
          "id": null,
          "outcome": null,
          "images": [
            {
              "image": "../../assets/images/non-pollen/placeholder.png",
              "imageWidthPx": 1
            },
            {
              "image": "../../assets/images/non-pollen/placeholder.png",
              "imageWidthPx": 1
            },
            {
              "image": "../../assets/images/non-pollen/placeholder.png",
              "imageWidthPx": 1
            },
            {
              "image": "../../assets/images/non-pollen/placeholder.png",
              "imageWidthPx": 1
            }
          ]
        }
      ]
    },
    "3": {
      "id": "3",
      "type": "step",
      "note": "-",
      "choices": [
        {
          "label": "Luchtzakken tot halfrond, zelden iets meer dan halfrond (zoals bij *Picea orientalis* en *P. omorica*). Vergelijk fig. 5n en o.",
          "next": null,
          "id": {
            "name": "6.2 Picea (Blz... 54)",
            "size": "-",
            "source": "-",
            "note": "-",
            "text": "-",
            "incomplete": false,
            "images": [
              {
                "image": "../../assets/images/non-pollen/placeholder.png",
                "imageWidthPx": 1
              },
              {
                "image": "../../assets/images/non-pollen/placeholder.png",
                "imageWidthPx": 1
              },
              {
                "image": "../../assets/images/non-pollen/placeholder.png",
                "imageWidthPx": 1
              },
              {
                "image": "../../assets/images/non-pollen/placeholder.png",
                "imageWidthPx": 1
              }
            ]
          },
          "outcome": null,
          "images": [
            {
              "image": "../../assets/images/non-pollen/placeholder.png",
              "imageWidthPx": 1
            },
            {
              "image": "../../assets/images/non-pollen/placeholder.png",
              "imageWidthPx": 1
            },
            {
              "image": "../../assets/images/non-pollen/placeholder.png",
              "imageWidthPx": 1
            },
            {
              "image": "../../assets/images/non-pollen/placeholder.png",
              "imageWidthPx": 1
            }
          ]
        },
        {
          "label": "Luchtzakken duidelijk meer dan halfrond.",
          "next": "4",
          "id": null,
          "outcome": null,
          "images": [
            {
              "image": "../../assets/images/non-pollen/placeholder.png",
              "imageWidthPx": 1
            },
            {
              "image": "../../assets/images/non-pollen/placeholder.png",
              "imageWidthPx": 1
            },
            {
              "image": "../../assets/images/non-pollen/placeholder.png",
              "imageWidthPx": 1
            },
            {
              "image": "../../assets/images/non-pollen/placeholder.png",
              "imageWidthPx": 1
            }
          ]
        }
      ]
    },
    "4": {
      "id": "4",
      "type": "step",
      "note": "-",
      "choices": [
        {
          "label": "Luchtzakken niet vanuit het equatoriaalgebied naar de ventrale zijde van het PMT verschoven (fig. 5a–f). PK ca. 50–110 µm lang, bij Midden-Europese soorten ca. 60 tot 100 µm.",
          "next": null,
          "id": {
            "name": "6.3 Pinus (Blz... 55)",
            "size": "-",
            "source": "-",
            "note": "-",
            "text": "-",
            "incomplete": false,
            "images": [
              {
                "image": "../../assets/images/non-pollen/placeholder.png",
                "imageWidthPx": 1
              },
              {
                "image": "../../assets/images/non-pollen/placeholder.png",
                "imageWidthPx": 1
              },
              {
                "image": "../../assets/images/non-pollen/placeholder.png",
                "imageWidthPx": 1
              },
              {
                "image": "../../assets/images/non-pollen/placeholder.png",
                "imageWidthPx": 1
              }
            ]
          },
          "outcome": null,
          "images": [
            {
              "image": "../../assets/images/non-pollen/placeholder.png",
              "imageWidthPx": 1
            },
            {
              "image": "../../assets/images/non-pollen/placeholder.png",
              "imageWidthPx": 1
            },
            {
              "image": "../../assets/images/non-pollen/placeholder.png",
              "imageWidthPx": 1
            },
            {
              "image": "../../assets/images/non-pollen/placeholder.png",
              "imageWidthPx": 1
            }
          ]
        },
        {
          "label": "Luchtzakken duidelijk naar de ventrale zijde van het PMT verschoven (fig. 8). PK 100–140 µm lang.",
          "next": null,
          "id": {
            "name": "6.4 Keteleeria davidiana (Blz... 59)",
            "size": "-",
            "source": "-",
            "note": "-",
            "text": "-",
            "incomplete": false,
            "images": [
              {
                "image": "../../assets/images/non-pollen/placeholder.png",
                "imageWidthPx": 1
              },
              {
                "image": "../../assets/images/non-pollen/placeholder.png",
                "imageWidthPx": 1
              },
              {
                "image": "../../assets/images/non-pollen/placeholder.png",
                "imageWidthPx": 1
              },
              {
                "image": "../../assets/images/non-pollen/placeholder.png",
                "imageWidthPx": 1
              }
            ]
          },
          "outcome": null,
          "images": [
            {
              "image": "../../assets/images/non-pollen/placeholder.png",
              "imageWidthPx": 1
            },
            {
              "image": "../../assets/images/non-pollen/placeholder.png",
              "imageWidthPx": 1
            },
            {
              "image": "../../assets/images/non-pollen/placeholder.png",
              "imageWidthPx": 1
            },
            {
              "image": "../../assets/images/non-pollen/placeholder.png",
              "imageWidthPx": 1
            }
          ]
        }
      ]
    },
    "5": {
      "id": "5",
      "type": "step",
      "note": "-",
      "choices": [
        {
          "label": "Luchtzakken meer dan halfrond, meestal driekwartbolvormig, Exine van het PMT dorsaal 6–10 µm dik (fig. 5 m). PK 95–190 µm, Europese soorten ca. 120 tot 160 µm lang.",
          "next": null,
          "id": {
            "name": "6.5 Abies (Blz... 59)",
            "size": "-",
            "source": "-",
            "note": "-",
            "text": "-",
            "incomplete": false,
            "images": [
              {
                "image": "../../assets/images/non-pollen/placeholder.png",
                "imageWidthPx": 1
              },
              {
                "image": "../../assets/images/non-pollen/placeholder.png",
                "imageWidthPx": 1
              },
              {
                "image": "../../assets/images/non-pollen/placeholder.png",
                "imageWidthPx": 1
              },
              {
                "image": "../../assets/images/non-pollen/placeholder.png",
                "imageWidthPx": 1
              }
            ]
          },
          "outcome": null,
          "images": [
            {
              "image": "../../assets/images/non-pollen/placeholder.png",
              "imageWidthPx": 1
            },
            {
              "image": "../../assets/images/non-pollen/placeholder.png",
              "imageWidthPx": 1
            },
            {
              "image": "../../assets/images/non-pollen/placeholder.png",
              "imageWidthPx": 1
            },
            {
              "image": "../../assets/images/non-pollen/placeholder.png",
              "imageWidthPx": 1
            }
          ]
        },
        {
          "label": "Luchtzakken meestal slechts halfrond, Exine van het PMT dorsaal 4–7 µm dik, aan de aanhechtingsplaats van de luchtzakken nog dikker (tabel 3: 6–7; fig. 5g–l). PK ca. 75–110 µm lang.",
          "next": null,
          "id": {
            "name": "6.6 Cedrus (Blz... 60)",
            "size": "-",
            "source": "-",
            "note": "-",
            "text": "-",
            "incomplete": false,
            "images": [
              {
                "image": "../../assets/images/non-pollen/placeholder.png",
                "imageWidthPx": 1
              },
              {
                "image": "../../assets/images/non-pollen/placeholder.png",
                "imageWidthPx": 1
              },
              {
                "image": "../../assets/images/non-pollen/placeholder.png",
                "imageWidthPx": 1
              },
              {
                "image": "../../assets/images/non-pollen/placeholder.png",
                "imageWidthPx": 1
              }
            ]
          },
          "outcome": null,
          "images": [
            {
              "image": "../../assets/images/non-pollen/placeholder.png",
              "imageWidthPx": 1
            },
            {
              "image": "../../assets/images/non-pollen/placeholder.png",
              "imageWidthPx": 1
            },
            {
              "image": "../../assets/images/non-pollen/placeholder.png",
              "imageWidthPx": 1
            },
            {
              "image": "../../assets/images/non-pollen/placeholder.png",
              "imageWidthPx": 1
            }
          ]
        }
      ]
    }
  }
}
