{
  "meta": {
    "key": "beug_tricolporatae_striate_rugulate_191_coronilla_sub",
    "title": "19.1 Coronilla-type (Beug) — interactieve sleutel (NL)",
    "locale": "nl",
    "source": "Vertaling (Duits → Nederlands) van door gebruiker aangeleverde paginascans bij Beug §19.1 Coronilla-Typ. PK = pollenkorrel, PFormI = pollenvormindex. Afbeeldingen niet opgenomen.",
    "stepCount": 1,
    "start": "1"
  },
  "start": "1",
  "steps": {
    "1": {
      "id": "1",
      "type": "step",
      "choices": [
        {
          "label": "PK niet groter dan 30(35) µm, vormstabiel. Valla smal en nauw, eventueel pas met olie-immersie of in het fasecontrastbeeld zichtbaar (Tafel 47: 19-22).",
          "outcome": {
            "text": "19.1 *Coronilla*-type (blz. 254)"
          }
        },
        {
          "label": "PK groter dan 38-52 µm, dunwandig, weinig vormstabiel. Valla kort. Sculpturering variabel, ook scabraat of verrucaat of polair onvolledig netvormig (Tafel 29: 11-15).",
          "outcome": {
            "text": "*Anthyllis vulneraria* (blz. 191)"
          }
        }
      ]
    }
  }
}
