{
  "meta": {
    "key": "beug_tricolporatae_reticulate_2225_ptelea_trifoliata_sub",
    "title": "22.25 Ptelea trifoliata (Beug) — interactieve sleutel (NL)",
    "locale": "nl",
    "source": "Vertaling (Duits → Nederlands) van door gebruiker aangeleverde paginascans bij Beug §22.25 Ptelea trifoliata. PK = pollenkorrel, PFieldI = poolveldindex. Afbeeldingen niet opgenomen.",
    "stepCount": 1,
    "start": "1"
  },
  "start": "1",
  "steps": {
    "1": {
      "id": "1",
      "type": "step",
      "choices": [
        {
          "label": "PK elliptisch, poriën enkel spaltaat, slechts 1-1,5 µm breed en 8-11 µm lang, contrastrijk, PK 25-32 µm groot. Poolfelder middelgroot. Wanneer poolfelder klein, vgl. 22.21. *Rheum* (Tafel 75: 29-34).",
          "outcome": {
            "text": "22.25 *Ptelea trifoliata* (blz. 342)"
          }
        },
        {
          "label": "Geen match. Ga terug naar de hoofdkey. [te verifiëren]"
        }
      ]
    }
  }
}