{
  "meta": {
    "key": "beug32-stephanoporatae.json",
    "title": "32 Stephanoporatae (Beug)",
    "locale": "nl",
    "source": "Beug",
    "stepCount": 13,
    "start": "1"
  },
  "start": "1",
  "steps": {
    "1": {
      "id": "1",
      "type": "step",
      "choices": [
        {
          "label": "PK psilaat of scabraat, met of zonder Tectum perforatum.",
          "next": "2"
        },
        {
          "label": "PK echinaat, microechinaat, reticulaat of rugulaat, Indien scabraat, dan Skulpturelemente met nur 1-2 µm afstand.",
          "next": "12"
        }
      ]
    },
    "2": {
      "id": "2",
      "type": "step",
      "choices": [
        {
          "label": "PK met Tectum perforatum, dikker Endexine en duidelijker columella-laag (Tafel 102: 22-25).",
          "outcome": {
            "text": "32.1 *Theligonum cynocrambe* (Blz. 442)"
          }
        },
        {
          "label": "Tectum niet perforiert.",
          "next": "3"
        }
      ]
    },
    "3": {
      "id": "3",
      "type": "step",
      "choices": [
        {
          "label": "PK zusätzlich met einzelnen Poriën auf einem Poolvelden, oblaat (Tafel 103: 5-9).",
          "outcome": {
            "text": "32.2 *Juglans* (Blz. 442)"
          }
        },
        {
          "label": "PK zonder zusätzliche Poriën auf einem Poolvelden.",
          "next": "4"
        }
      ]
    },
    "4": {
      "id": "4",
      "type": "step",
      "choices": [
        {
          "label": "PK auf beiden poolvelden met bogenförmigen, von Porie zu Porie verlaufenden Verdickungen des Tectums (arcus), Indien zonder arcus, dan met einem knik in der Exine anstelle der arcus (Tafel 102: 8-21).",
          "outcome": {
            "text": "32.3 *Alnus* (Blz. 444)"
          }
        },
        {
          "label": "PK zonder arcus en zonder knik in der Exine anstelle der arcus.",
          "next": "5"
        }
      ]
    },
    "5": {
      "id": "5",
      "type": "step",
      "choices": [
        {
          "label": "PK psilaat, Exine 1,7-1,9 µm dik, met dik Tectum en dunner columella-laag. Poriën 3,5-4,5 µm groot, met annulus (Tafel 103: 1-4).",
          "outcome": {
            "text": "32.4 *Celtis* (Blz. 446)"
          }
        },
        {
          "label": "Tectum niet opvallend dik, columella's niet herkenbaar.",
          "next": "6"
        }
      ]
    },
    "6": {
      "id": "6",
      "type": "step",
      "choices": [
        {
          "label": "PK met vestibulum.",
          "next": "7"
        },
        {
          "label": "PK zonder vestibulum, Poriën met einem sterk of wenig sterk vorspringenden annulus of zonder annulus.",
          "next": "8"
        }
      ]
    },
    "7": {
      "id": "7",
      "type": "step",
      "choices": [
        {
          "label": "PK 34-42 µm groot, met 5-6(7) Poriën en (fasecontrast) runden, ca. 0,5 µm großen Skulpturelementen (Microverrucae), Poolvelden met je 2-3 ca. 8-10 µm großen, lacuna-achtige indrukken (Tafel 103: 10-15).",
          "outcome": {
            "text": "32.5 *Pterocarya* (Blz. 448)"
          }
        },
        {
          "label": "PK 37-48 µm groot, met 3-5(6) Poriën, Exine psilaat, Poolvelden zonder lacunae-artige indrukken (Tafel 104: 5-7).",
          "outcome": {
            "text": "32.6 *Carpinus betulus* (Blz. 448)"
          }
        }
      ]
    },
    "8": {
      "id": "8",
      "type": "step",
      "choices": [
        {
          "label": "Endexine auf der Innenseite rauh tot schollig, vooral im gebied der porierand (costae), Poriën met annulus, vaak duidelijk voorstehend (Tafel 104: 1-3).",
          "outcome": {
            "text": "32.7 *Nerium oleander* (Blz. 448)"
          }
        },
        {
          "label": "Endexine auf der Innenseite glad.",
          "next": "9"
        }
      ]
    },
    "9": {
      "id": "9",
      "type": "step",
      "choices": [
        {
          "label": "Exine höchstens ca. 0,8 µm dik, Poriën met smalle annulus, of met einer schwachen Aufbiegung der Porenumrandungen of zonder annulus (Tafel 101: 17-29).",
          "outcome": {
            "text": "*Urticaceae*, *Moraceae* (Blz. 436)"
          }
        },
        {
          "label": "Exine dikker, Poriën met zeer breed en dik annulus.",
          "next": "10"
        }
      ]
    },
    "10": {
      "id": "10",
      "type": "step",
      "choices": [
        {
          "label": "Poriën mehr of weniger gelijkmatig am Äquator angeordnet.",
          "next": "11"
        },
        {
          "label": "PK in Polaransticht met 2 miteinander gegenüber liegenden Gruppen von (1)2-3(4) Poriën (Tafel 104: 8-12).",
          "outcome": {
            "text": "32.8 *Myriophyllum alterniflorum* (Blz. 448)"
          }
        }
      ]
    },
    "11": {
      "id": "11",
      "type": "step",
      "choices": [
        {
          "label": "verdikking der Anuli erfolgt abrupt (Tafel 104: 13-16).",
          "outcome": {
            "text": "32.9 *Myriophyllum spicatum* (Blz. 448)"
          }
        },
        {
          "label": "verdikking der Anuli erfolgt allmählich (Tafel 104: 17-18).",
          "outcome": {
            "text": "32.10 *Myriophyllum verticillatum* (Blz. 448)"
          }
        }
      ]
    },
    "12": {
      "id": "12",
      "type": "step",
      "choices": [
        {
          "label": "PK echinaat, microechinaat of scabraat, Poriën met auffälligen costae (Tafel 105: 1-18).",
          "next": "beug_stephanoporatae_3211_campanulaceae_sub"
        },
        {
          "label": "PK rugulaat of reticulaat.",
          "next": "13"
        }
      ]
    },
    "13": {
      "id": "13",
      "type": "step",
      "choices": [
        {
          "label": "PK sferoïdisch (pollenvormindex <1,0), perreticulaat, Brochi 0,8-1,4(1,8) µm groot, Exine met columella-laag (Tafel 104: 19-22).",
          "outcome": {
            "text": "32.12 *Pistacia* (Blz. 453)"
          }
        },
        {
          "label": "PK oblaat, rugulaat of met tot zu 2-5 µm großen suprareticulaten, vaak onvolledig gesloten Brochi, omranding der Poriën verdikt, columella-laag ontbreekt (Tafel 105: 19-25).",
          "outcome": {
            "text": "32.13 *Ulmus*, *Zelkova* (Blz. 454)"
          }
        }
      ]
    }
  }
}