{
  "meta": {
    "key": "beug32-stephanoporatae-jasione",
    "title": "32.11.1 *Jasione montana*-type (Tafel 105: 1–3)",
    "locale": "nl",
    "source": "Beug",
    "note": "-",
    "start": "1",
    "stepCount": 1
  },
  "start": "1",
  "steps": {
    "1": {
      "id": "1",
      "type": "step",
      "choices": [
        {
          "label": "Microechini/scabraat ≤ ca. 0,5 µm; meestal 3 poriën; 23–30 µm.",
          "outcome": {
            "text": "32.11.1 *Jasione montana*-type\n\nPK relatief klein (23,0–30,0 µm); sculptuurelementen tot ca. 0,5 µm, in optische snede niet of nauwelijks meetbaar; afstanden 1–2 µm. Overwegend 3 poriën.\n\n*Jasione montana* L. (2)\n23,0–29,5 µm, MiW 25,8 µm; 50 PK, 1a, Ä\n[te verifiëren: OCR «50 PL» als 50 PK gelezen]\n\n*Wahlenbergia hederacea* (L.) RCHB. (2)\n23,3–30,0 µm, MiW 27,2 µm; 50 PK, 0a, Ä",
            "pollen_key": "jasione_montana"
          }
        }
      ]
    }
  }
}
